django_ixp_tracker-1.3.2.dist-info/licenses/LICENSE
ixp_tracker/__init__.py
ixp_tracker/apps.py
ixp_tracker/conf.py
ixp_tracker/data_lookup.py
ixp_tracker/importers.py
ixp_tracker/models.py
ixp_tracker/stats.py
ixp_tracker/management/__init__.py
ixp_tracker/management/commands/__init__.py
ixp_tracker/management/commands/ixp_tracker_import.py
ixp_tracker/migrations/0001_initial.py
ixp_tracker/migrations/0002_asn_asn_unique_as_number.py
ixp_tracker/migrations/0003_alter_asn_name.py
ixp_tracker/migrations/0004_ixpmember_ixpmember_unique_ixp_membership.py
ixp_tracker/migrations/0005_statspercountry_statsperixp_and_more.py
ixp_tracker/migrations/0006_remove_statspercountry_ixp_tracker_unique_per_country_stats_and_more.py
ixp_tracker/migrations/0007_remove_ixpmember_date_left_and_more.py
ixp_tracker/migrations/0008_alter_asn_id_alter_ixp_id_alter_ixpmember_id_and_more.py
ixp_tracker/migrations/0009_alter_ixpmembershiprecord_member.py
ixp_tracker/migrations/0010_statspercountry_ixp_count.py
ixp_tracker/migrations/0011_statsperixp_rs_peering_rate.py
ixp_tracker/migrations/0012_statspercountry_routed_asn_count_and_more.py
ixp_tracker/migrations/0013_ixp_manrs_participant.py
ixp_tracker/migrations/0014_statsperixp_members_joined_last_12_months_and_more.py
ixp_tracker/migrations/0015_statsperixp_monthly_members_change_and_more.py
ixp_tracker/migrations/0016_statspercountry_routed_asns_ixp_member_customers_rate_and_more.py
ixp_tracker/migrations/0017_ixp_org_id.py
ixp_tracker/migrations/0018_ixp_anchor_host.py
ixp_tracker/migrations/0019_statspercountry_last_generated_and_more.py
ixp_tracker/migrations/0020_ixp_physical_locations.py
ixp_tracker/migrations/__init__.py
django_ixp_tracker-1.3.2.dist-info/METADATA
django_ixp_tracker-1.3.2.dist-info/WHEEL
django_ixp_tracker-1.3.2.dist-info/top_level.txt
django_ixp_tracker-1.3.2.dist-info/RECORD
