Metadata-Version: 2.4
Name: django-ixp-tracker
Version: 1.3.2
Summary: Library to retrieve and manipulate data about IXPs
Author: Internet Society
License: Apache-2.0
Project-URL: Homepage, https://github.com/InternetSociety/django-ixp-tracker
Project-URL: Changelog, https://github.com/InternetSociety/django-ixp-tracker/releases
Project-URL: Issues, https://github.com/InternetSociety/django-ixp-tracker/issues
Project-URL: CI, https://github.com/InternetSociety/django-ixp-tracker/actions
Classifier: License :: OSI Approved :: Apache Software License
Classifier: Programming Language :: Python :: 3
Classifier: Operating System :: OS Independent
Classifier: Framework :: Django
Requires-Python: >=3.10
License-File: LICENSE
Requires-Dist: django>=5.2
Requires-Dist: django-countries>7.6
Requires-Dist: python-dateutil
Requires-Dist: requests
Requires-Dist: typing-extensions
Provides-Extra: test
Requires-Dist: django-stubs; extra == "test"
Requires-Dist: factory-boy; extra == "test"
Requires-Dist: pre-commit; extra == "test"
Requires-Dist: pytest; extra == "test"
Requires-Dist: pytest-django; extra == "test"
Requires-Dist: responses; extra == "test"
Dynamic: license-file
